sectoralarm/__init__.py
sectoralarm/actions.py
sectoralarm/cache.py
sectoralarm/client.py
sectoralarm/endpoints.py
sectoralarm/exceptions.py
sectoralarm/main.py
sectoralarm/utils.py
sectoralarm-1.2.0.dist-info/METADATA
sectoralarm-1.2.0.dist-info/WHEEL
sectoralarm-1.2.0.dist-info/entry_points.txt
sectoralarm-1.2.0.dist-info/top_level.txt
sectoralarm-1.2.0.dist-info/RECORD
