Metadata-Version: 2.1
Name: sectoralarm
Version: 1.2.0
Summary: A Python library for interacting with the Sector Alarm API.
Home-page: https://github.com/garnser/sector_alarm
Author: Jonathan Petersson
Author-email: jpetersson@garnser.se
Project-URL: Bug Tracker, https://github.com/garnser/sector_alarm/issues
Classifier: Programming Language :: Python :: 3
Classifier: License :: OSI Approved :: MIT License
Classifier: Operating System :: OS Independent
Requires-Python: >=3.6
Requires-Dist: requests
